[{"Id":1,"Nome":"Felipe Dias Amorim","Email":"vanessa.dias@test.com","CPF":"123.456.789-00","RG":"12.345.678-0","Contatos":[{"Id":0,"Tipo":"Celular","DDD":11,"Telefone":9876543210.0}],"Enderecos":[{"Id":0,"Tipo":"Entrega","CEP":"43125-678","Logradouro":"Rua Exemplo","Numero":123,"Bairro":"Centro","Complemento":"Apto 101","Cidade":"Cidade Exemplo","Estado":"EX","Referencia":"Perto da praça"}]},{"Id":3,"Nome":"Vanessa Dias Amorim","Email":"felipe.dias@test.com","CPF":"123.456.789-00","RG":"12.345.678-0","Contatos":[{"Id":0,"Tipo":"Celular","DDD":11,"Telefone":9876543210.0}],"Enderecos":[{"Id":0,"Tipo":"Entrega","CEP":"12345-678","Logradouro":"Rua Exemplo","Numero":123,"Bairro":"Centro","Complemento":"Apto 101","Cidade":"Cidade Exemplo","Estado":"EX","Referencia":"Perto da praça"}]}]